[{"isbn_c_p":"9781260501834_10.2_10E","link":"https://yadi.sk/i/X8eLlB_GQ2OC6w"},{"isbn_c_p":"9781260501834_10.2_11E","link":"https://yadi.sk/i/JzEXQVmPiWOy2A"},{"isbn_c_p":"9781260501834_10.2_12E","link":"https://yadi.sk/i/jRcd_JfCUl5Nxg"},{"isbn_c_p":"9781260501834_10.2_13E","link":"https://yadi.sk/i/eA31igEMQfY99w"},{"isbn_c_p":"9781260501834_10.2_14E","link":"https://yadi.sk/i/sRee5nRGaawl7g"},{"isbn_c_p":"9781260501834_10.2_15E","link":"https://yadi.sk/i/_62WfX0_z8BDJQ"},{"isbn_c_p":"9781260501834_10.2_16E","link":"https://yadi.sk/i/7KsZRQf-2gF7SA"},{"isbn_c_p":"9781260501834_10.2_17E","link":"https://yadi.sk/i/bpowICIxNrnagw"},{"isbn_c_p":"9781260501834_10.2_18E","link":"https://yadi.sk/i/vZhXgw7T0L9Y-w"},{"isbn_c_p":"9781260501834_10.2_19E","link":"https://yadi.sk/i/iI4bQBNAWqMHgA"},{"isbn_c_p":"9781260501834_10.2_1E","link":"https://yadi.sk/i/_AoJQzVLVDoVdQ"},{"isbn_c_p":"9781260501834_10.2_20E","link":"https://yadi.sk/i/fiZNzpV3nC65Zw"},{"isbn_c_p":"9781260501834_10.2_21E","link":"https://yadi.sk/i/Gr12tbOtu4Q1WQ"},{"isbn_c_p":"9781260501834_10.2_22E","link":"https://yadi.sk/i/fUPhrEDTvMRHOg"},{"isbn_c_p":"9781260501834_10.2_23E","link":"https://yadi.sk/i/9LwulDM9onD2eA"},{"isbn_c_p":"9781260501834_10.2_24E","link":"https://yadi.sk/i/JR4GO-3w_kohww"},{"isbn_c_p":"9781260501834_10.2_25E","link":"https://yadi.sk/i/OBQxuJpRfd_qOQ"},{"isbn_c_p":"9781260501834_10.2_26E","link":"https://yadi.sk/i/gxfd837qbd_oRA"},{"isbn_c_p":"9781260501834_10.2_27E","link":"https://yadi.sk/i/jEDvlElQ6JPoLA"},{"isbn_c_p":"9781260501834_10.2_28E","link":"https://yadi.sk/i/owhUJmGoJDtHFw"},{"isbn_c_p":"9781260501834_10.2_29E","link":"https://yadi.sk/i/NJ_QcmJf6Fpx1g"},{"isbn_c_p":"9781260501834_10.2_2E","link":"https://yadi.sk/i/2ttSSG0duO2b_A"},{"isbn_c_p":"9781260501834_10.2_30E","link":"https://yadi.sk/i/2QWqnJK_T2ur4Q"},{"isbn_c_p":"9781260501834_10.2_31E","link":"https://yadi.sk/i/rJLEx19juO21-Q"},{"isbn_c_p":"9781260501834_10.2_32E","link":"https://yadi.sk/i/1ev0eZB0T_azcA"},{"isbn_c_p":"9781260501834_10.2_33E","link":"https://yadi.sk/i/A_-8TUiGe9FVxQ"},{"isbn_c_p":"9781260501834_10.2_34E","link":"https://yadi.sk/i/IB2VcBAIT70-Qg"},{"isbn_c_p":"9781260501834_10.2_35E","link":"https://yadi.sk/i/9ZlXbOQhSkXfKA"},{"isbn_c_p":"9781260501834_10.2_36E","link":"https://yadi.sk/i/H7UNJxs4MrnPxQ"},{"isbn_c_p":"9781260501834_10.2_37E","link":"https://yadi.sk/i/wPkZ8E3i7MC41A"},{"isbn_c_p":"9781260501834_10.2_38E","link":"https://yadi.sk/i/wUsFmV5X40LX1w"},{"isbn_c_p":"9781260501834_10.2_39E","link":"https://yadi.sk/i/aR3Jgb2ygdnDxw"},{"isbn_c_p":"9781260501834_10.2_3E","link":"https://yadi.sk/i/NMboKZ9zhl9Crw"},{"isbn_c_p":"9781260501834_10.2_40E","link":"https://yadi.sk/i/3muRoUxiKeJdsQ"},{"isbn_c_p":"9781260501834_10.2_41E","link":"https://yadi.sk/i/KYsNsCPP3i7LtQ"},{"isbn_c_p":"9781260501834_10.2_42E","link":"https://yadi.sk/i/q3H5Pp9r2SdPiQ"},{"isbn_c_p":"9781260501834_10.2_43E","link":"https://yadi.sk/i/Z5JdWt-82tnWdA"},{"isbn_c_p":"9781260501834_10.2_44E","link":"https://yadi.sk/i/R9AlDEtq_-P5vw"},{"isbn_c_p":"9781260501834_10.2_45E","link":"https://yadi.sk/i/srLhlUu1Mksv7g"},{"isbn_c_p":"9781260501834_10.2_46E","link":"https://yadi.sk/i/yIjtKuO7awrqIQ"},{"isbn_c_p":"9781260501834_10.2_47E","link":"https://yadi.sk/i/LoRtZpGrAQsOXQ"},{"isbn_c_p":"9781260501834_10.2_48E","link":"https://yadi.sk/i/PbjXhZnS_Owf8A"},{"isbn_c_p":"9781260501834_10.2_49E","link":"https://yadi.sk/i/sVuqi3GtPEEnYQ"},{"isbn_c_p":"9781260501834_10.2_4E","link":"https://yadi.sk/i/ptSqScN4Qhs_yA"},{"isbn_c_p":"9781260501834_10.2_50E","link":"https://yadi.sk/i/Lksk3-Opj8t76g"},{"isbn_c_p":"9781260501834_10.2_51E","link":"https://yadi.sk/i/28dadyDEIi0bag"},{"isbn_c_p":"9781260501834_10.2_52E","link":"https://yadi.sk/i/rKTu09ksoQ4Y5A"},{"isbn_c_p":"9781260501834_10.2_53E","link":"https://yadi.sk/i/z-NcIBtyK9GDdQ"},{"isbn_c_p":"9781260501834_10.2_54E","link":"https://yadi.sk/i/cQovEweWlC0t3g"},{"isbn_c_p":"9781260501834_10.2_55E","link":"https://yadi.sk/i/T9uzHtD4TC1MVw"},{"isbn_c_p":"9781260501834_10.2_56E","link":"https://yadi.sk/i/MEAQfJM9PiTfZg"},{"isbn_c_p":"9781260501834_10.2_57E","link":"https://yadi.sk/i/Oqk8MrJ7k6IyjQ"},{"isbn_c_p":"9781260501834_10.2_58E","link":"https://yadi.sk/i/owkGpGiiv0VIFQ"},{"isbn_c_p":"9781260501834_10.2_59E","link":"https://yadi.sk/i/qkE8MwvwJ5TQnA"},{"isbn_c_p":"9781260501834_10.2_5E","link":"https://yadi.sk/i/uI5Y-09ToRpvgg"},{"isbn_c_p":"9781260501834_10.2_60E","link":"https://yadi.sk/i/NBoPjhcdCvUnIQ"},{"isbn_c_p":"9781260501834_10.2_61E","link":"https://yadi.sk/i/FBwb_bVwuGiN6Q"},{"isbn_c_p":"9781260501834_10.2_62E","link":"https://yadi.sk/i/ifOZsxu8_UcoKw"},{"isbn_c_p":"9781260501834_10.2_63E","link":"https://yadi.sk/i/BwvZshdWBMoDcQ"},{"isbn_c_p":"9781260501834_10.2_64E","link":"https://yadi.sk/i/1pWHAORmUsYXgg"},{"isbn_c_p":"9781260501834_10.2_65E","link":"https://yadi.sk/i/AlT-Mh-cRzXFNg"},{"isbn_c_p":"9781260501834_10.2_66E","link":"https://yadi.sk/i/RoHuokEWmowJoQ"},{"isbn_c_p":"9781260501834_10.2_6E","link":"https://yadi.sk/i/dBvIz1ZOIaDpYg"},{"isbn_c_p":"9781260501834_10.2_7E","link":"https://yadi.sk/i/5fGOOFp0DIfyPA"},{"isbn_c_p":"9781260501834_10.2_8E","link":"https://yadi.sk/i/DTLLZno0dAUIqw"},{"isbn_c_p":"9781260501834_10.2_9E","link":"https://yadi.sk/i/lfJ6mMZ7jWaMgw"}]