[{"isbn_c_p":"9781319030483_9_10P","link":"https://yadi.sk/i/zn059yays9vxUw"},{"isbn_c_p":"9781319030483_9_11P","link":"https://yadi.sk/i/LYTSB-RW6j0OVA"},{"isbn_c_p":"9781319030483_9_12P","link":"https://yadi.sk/i/UjJEGKv9l8mfxg"},{"isbn_c_p":"9781319030483_9_13P","link":"https://yadi.sk/i/zSDys_CzJjE0Tg"},{"isbn_c_p":"9781319030483_9_14P","link":"https://yadi.sk/i/V3twM74BYUtXaQ"},{"isbn_c_p":"9781319030483_9_15P","link":"https://yadi.sk/i/er09EA8RwzYYjA"},{"isbn_c_p":"9781319030483_9_16P","link":"https://yadi.sk/i/WIhl8X6EZ4Ho3g"},{"isbn_c_p":"9781319030483_9_17P","link":"https://yadi.sk/i/jw9oboePQgE6SA"},{"isbn_c_p":"9781319030483_9_18P","link":"https://yadi.sk/i/voex0U0w77WkCg"},{"isbn_c_p":"9781319030483_9_19P","link":"https://yadi.sk/i/f7fpxGY0jl4-eg"},{"isbn_c_p":"9781319030483_9_1P","link":"https://yadi.sk/i/xGT5nuLALJi68g"},{"isbn_c_p":"9781319030483_9_20P","link":"https://yadi.sk/i/iZVwL1WvNveYeQ"},{"isbn_c_p":"9781319030483_9_21P","link":"https://yadi.sk/i/g1W3RVdRAwLfyg"},{"isbn_c_p":"9781319030483_9_22P","link":"https://yadi.sk/i/oxu30teO3nPtsA"},{"isbn_c_p":"9781319030483_9_23P","link":"https://yadi.sk/i/wwlZA_3MNjTWQQ"},{"isbn_c_p":"9781319030483_9_24P","link":"https://yadi.sk/i/NUXShWH6LKKNJA"},{"isbn_c_p":"9781319030483_9_25P","link":"https://yadi.sk/i/TtSA_1pEOEStCQ"},{"isbn_c_p":"9781319030483_9_26P","link":"https://yadi.sk/i/UkPhUzHYsLSzKw"},{"isbn_c_p":"9781319030483_9_27P","link":"https://yadi.sk/i/zTjqIMdw7PDKrQ"},{"isbn_c_p":"9781319030483_9_28P","link":"https://yadi.sk/i/p31PoQZwHX1W-Q"},{"isbn_c_p":"9781319030483_9_29P","link":"https://yadi.sk/i/_wBfD6nN38J0rA"},{"isbn_c_p":"9781319030483_9_2P","link":"https://yadi.sk/i/BQtoLBfuuXLbUQ"},{"isbn_c_p":"9781319030483_9_30P","link":"https://yadi.sk/i/xgZS5yfamq0mag"},{"isbn_c_p":"9781319030483_9_31P","link":"https://yadi.sk/i/3ycupK3EPMNOKg"},{"isbn_c_p":"9781319030483_9_32P","link":"https://yadi.sk/i/i6r2-E7YKmleiA"},{"isbn_c_p":"9781319030483_9_33P","link":"https://yadi.sk/i/CDLrIx9ISBtfSw"},{"isbn_c_p":"9781319030483_9_34P","link":"https://yadi.sk/i/PQ-xLmq1mfiPMA"},{"isbn_c_p":"9781319030483_9_35P","link":"https://yadi.sk/i/dcCyNSlgX-DO1g"},{"isbn_c_p":"9781319030483_9_36P","link":"https://yadi.sk/i/NHjRCvZofXl7CQ"},{"isbn_c_p":"9781319030483_9_37P","link":"https://yadi.sk/i/kZ7I_8CIRR5Bqw"},{"isbn_c_p":"9781319030483_9_38P","link":"https://yadi.sk/i/1txCVW34bM1-HA"},{"isbn_c_p":"9781319030483_9_39P","link":"https://yadi.sk/i/vCkk5cIBu9YasA"},{"isbn_c_p":"9781319030483_9_3P","link":"https://yadi.sk/i/O6efk1Eu9DJd1w"},{"isbn_c_p":"9781319030483_9_40P","link":"https://yadi.sk/i/TfHYYlWQjkLHeA"},{"isbn_c_p":"9781319030483_9_41P","link":"https://yadi.sk/i/C5mjpFydlezK6w"},{"isbn_c_p":"9781319030483_9_42P","link":"https://yadi.sk/i/cYhgiip866AiGA"},{"isbn_c_p":"9781319030483_9_43P","link":"https://yadi.sk/i/Aw6etPCeYaz5fw"},{"isbn_c_p":"9781319030483_9_44P","link":"https://yadi.sk/i/3tZBE-JbQqJkWA"},{"isbn_c_p":"9781319030483_9_45P","link":"https://yadi.sk/i/SYguBUX0CUcoHQ"},{"isbn_c_p":"9781319030483_9_46P","link":"https://yadi.sk/i/qrGxJJHMG3pf_A"},{"isbn_c_p":"9781319030483_9_47P","link":"https://yadi.sk/i/aacSkfvbMtnm_g"},{"isbn_c_p":"9781319030483_9_48P","link":"https://yadi.sk/i/G-e0xvcXClLlkQ"},{"isbn_c_p":"9781319030483_9_49P","link":"https://yadi.sk/i/eWxbG_maG0_01A"},{"isbn_c_p":"9781319030483_9_4P","link":"https://yadi.sk/i/W0ROtkpDevaRSQ"},{"isbn_c_p":"9781319030483_9_50P","link":"https://yadi.sk/i/NzoHMMpirSPD2A"},{"isbn_c_p":"9781319030483_9_5P","link":"https://yadi.sk/i/DJPV1xhbS3GTvg"},{"isbn_c_p":"9781319030483_9_6P","link":"https://yadi.sk/i/KhP6QexAsCUJ9w"},{"isbn_c_p":"9781319030483_9_7P","link":"https://yadi.sk/i/WUJ3EbSu02fnqg"},{"isbn_c_p":"9781319030483_9_8P","link":"https://yadi.sk/i/gkru9zoEozesFg"},{"isbn_c_p":"9781319030483_9_9P","link":"https://yadi.sk/i/lt-rQg7zWAvHWA"}]