[{"isbn_c_p":"9780133128741_1_10RQ","link":"https://yadi.sk/i/M-Yye9Kk47njrw"},{"isbn_c_p":"9780133128741_1_11RQ","link":"https://yadi.sk/i/NGgE8HX-sLVXHg"},{"isbn_c_p":"9780133128741_1_12RQ","link":"https://yadi.sk/i/E8_7qYYgIQq4qw"},{"isbn_c_p":"9780133128741_1_13RQ","link":"https://yadi.sk/i/MddZMYid2x4w6g"},{"isbn_c_p":"9780133128741_1_14RQ","link":"https://yadi.sk/i/FolBDg93IcSwzw"},{"isbn_c_p":"9780133128741_1_15RQ","link":"https://yadi.sk/i/Ltk_TT_GA7PEiw"},{"isbn_c_p":"9780133128741_1_16RQ","link":"https://yadi.sk/i/XFpwqqp8YrycYQ"},{"isbn_c_p":"9780133128741_1_17RQ","link":"https://yadi.sk/i/-RQoEN54ERtQzQ"},{"isbn_c_p":"9780133128741_1_18RQ","link":"https://yadi.sk/i/czSphUIRDyLR9g"},{"isbn_c_p":"9780133128741_1_19RQ","link":"https://yadi.sk/i/wAYwVoH4D43x1w"},{"isbn_c_p":"9780133128741_1_1RQ","link":"https://yadi.sk/i/q8HHieY0USIrgw"},{"isbn_c_p":"9780133128741_1_20RQ","link":"https://yadi.sk/i/ZoUzz_hpgRIFqg"},{"isbn_c_p":"9780133128741_1_21QP","link":"https://yadi.sk/i/B491xXKmXucU2A"},{"isbn_c_p":"9780133128741_1_22QP","link":"https://yadi.sk/i/YleQw6HMg0086Q"},{"isbn_c_p":"9780133128741_1_23QP","link":"https://yadi.sk/i/7UudXS5wj2kTxg"},{"isbn_c_p":"9780133128741_1_24QP","link":"https://yadi.sk/i/jbKWxs2GRBxdPw"},{"isbn_c_p":"9780133128741_1_25QP","link":"https://yadi.sk/i/vygTth9y5rACVw"},{"isbn_c_p":"9780133128741_1_26QP","link":"https://yadi.sk/i/7XKPgo2mdSyqVA"},{"isbn_c_p":"9780133128741_1_27QP","link":"https://yadi.sk/i/y3LHD_yFM27Aww"},{"isbn_c_p":"9780133128741_1_28QP","link":"https://yadi.sk/i/3nijaigIJbgt_g"},{"isbn_c_p":"9780133128741_1_29QP","link":"https://yadi.sk/i/W13X0wZmxsU37w"},{"isbn_c_p":"9780133128741_1_2RQ","link":"https://yadi.sk/i/NoGSKPMw6aO0hg"},{"isbn_c_p":"9780133128741_1_30QP","link":"https://yadi.sk/i/D5VZSlggv-pNQw"},{"isbn_c_p":"9780133128741_1_31QP","link":"https://yadi.sk/i/GCQ7W-VNlqDi7g"},{"isbn_c_p":"9780133128741_1_32QP","link":"https://yadi.sk/i/lYdk67Syz4GKjQ"},{"isbn_c_p":"9780133128741_1_33QP","link":"https://yadi.sk/i/rSojlejSYuoJWg"},{"isbn_c_p":"9780133128741_1_34QP","link":"https://yadi.sk/i/nS397p9jXCD5KQ"},{"isbn_c_p":"9780133128741_1_35QP","link":"https://yadi.sk/i/MD5QeE5nCCDLuw"},{"isbn_c_p":"9780133128741_1_36QP","link":"https://yadi.sk/i/5h4sWb_9R9--VQ"},{"isbn_c_p":"9780133128741_1_37QP","link":"https://yadi.sk/i/hjSn5-5nqpzdOg"},{"isbn_c_p":"9780133128741_1_38QP","link":"https://yadi.sk/i/QVZNh70IOEwnmg"},{"isbn_c_p":"9780133128741_1_39QP","link":"https://yadi.sk/i/aewWWAazhTQvkA"},{"isbn_c_p":"9780133128741_1_3RQ","link":"https://yadi.sk/i/38fpesfX_XCmEA"},{"isbn_c_p":"9780133128741_1_40QP","link":"https://yadi.sk/i/TxF5LDIPIYdimw"},{"isbn_c_p":"9780133128741_1_41QP","link":"https://yadi.sk/i/hQMs6XzvW1QQQg"},{"isbn_c_p":"9780133128741_1_42QP","link":"https://yadi.sk/i/AOXxt7qZpdMtyg"},{"isbn_c_p":"9780133128741_1_43QP","link":"https://yadi.sk/i/hfMbdovqrVar7w"},{"isbn_c_p":"9780133128741_1_44QP","link":"https://yadi.sk/i/oRGWxhLaaVDlrg"},{"isbn_c_p":"9780133128741_1_45QP","link":"https://yadi.sk/i/I8_GUnoHkYcqWQ"},{"isbn_c_p":"9780133128741_1_46QP","link":"https://yadi.sk/i/YD953S8Slc5yjQ"},{"isbn_c_p":"9780133128741_1_47QP","link":"https://yadi.sk/i/AqddW1NkRWUoNA"},{"isbn_c_p":"9780133128741_1_48QP","link":"https://yadi.sk/i/jXvx7wWBpGYMgg"},{"isbn_c_p":"9780133128741_1_49QP","link":"https://yadi.sk/i/ghST-wQmxcYa-A"},{"isbn_c_p":"9780133128741_1_4RQ","link":"https://yadi.sk/i/QTigS3ltJnM_uw"},{"isbn_c_p":"9780133128741_1_50QP","link":"https://yadi.sk/i/FSKJzFln4VDOoA"},{"isbn_c_p":"9780133128741_1_51QP","link":"https://yadi.sk/i/c2-xtA5fpeW8xg"},{"isbn_c_p":"9780133128741_1_52QP","link":"https://yadi.sk/i/wRI_C4wXaoH1Kw"},{"isbn_c_p":"9780133128741_1_53QP","link":"https://yadi.sk/i/BhnNlmNfy5n_YA"},{"isbn_c_p":"9780133128741_1_54SDP","link":"https://yadi.sk/i/8mLdydmWR5_LWQ"},{"isbn_c_p":"9780133128741_1_55SDP","link":"https://yadi.sk/i/Mb7c2hXvTf1h0A"},{"isbn_c_p":"9780133128741_1_56SDP","link":"https://yadi.sk/i/Mf0D_pLYoEoLCw"},{"isbn_c_p":"9780133128741_1_57SDP","link":"https://yadi.sk/i/nMmIfmV9xLWMYw"},{"isbn_c_p":"9780133128741_1_58SDP","link":"https://yadi.sk/i/a6Ga51pKxNpDCQ"},{"isbn_c_p":"9780133128741_1_59SDP","link":"https://yadi.sk/i/hdvUEPt0j6h5fw"},{"isbn_c_p":"9780133128741_1_5RQ","link":"https://yadi.sk/i/MJokviBss8doFg"},{"isbn_c_p":"9780133128741_1_60SDP","link":"https://yadi.sk/i/DY5Q-7fcVZNNNQ"},{"isbn_c_p":"9780133128741_1_6RQ","link":"https://yadi.sk/i/vR8DWPzfLCXR2A"},{"isbn_c_p":"9780133128741_1_7RQ","link":"https://yadi.sk/i/ooF-N3BHCGzC2g"},{"isbn_c_p":"9780133128741_1_8RQ","link":"https://yadi.sk/i/JB2YcXMZ6iUfgw"},{"isbn_c_p":"9780133128741_1_9RQ","link":"https://yadi.sk/i/ETIIIz5yx0ZGig"}]