[{"isbn_c_p":"9780078021558_15_10P","link":"https://yadi.sk/i/LO-u7bIIKhaT6w"},{"isbn_c_p":"9780078021558_15_11P","link":"https://yadi.sk/i/WW8CjYZgIAzxxA"},{"isbn_c_p":"9780078021558_15_12P","link":"https://yadi.sk/i/6MxGYDC8jXaVgQ"},{"isbn_c_p":"9780078021558_15_13P","link":"https://yadi.sk/i/y68BonrqM_gZbQ"},{"isbn_c_p":"9780078021558_15_14P","link":"https://yadi.sk/i/ou1ogt289Atu0g"},{"isbn_c_p":"9780078021558_15_15P","link":"https://yadi.sk/i/j7uPKw1OBp_MLQ"},{"isbn_c_p":"9780078021558_15_16P","link":"https://yadi.sk/i/oIi9o7yZgbA5NQ"},{"isbn_c_p":"9780078021558_15_17P","link":"https://yadi.sk/i/KCdZmA3O7X6uQg"},{"isbn_c_p":"9780078021558_15_18P","link":"https://yadi.sk/i/ba--Yu36k6rpbw"},{"isbn_c_p":"9780078021558_15_19P","link":"https://yadi.sk/i/l941O6w__9abUw"},{"isbn_c_p":"9780078021558_15_1P","link":"https://yadi.sk/i/W6WG0xZJakRicw"},{"isbn_c_p":"9780078021558_15_20P","link":"https://yadi.sk/i/DDk-IGSa3HG-hQ"},{"isbn_c_p":"9780078021558_15_21P","link":"https://yadi.sk/i/s9ltlAqG52W7Kg"},{"isbn_c_p":"9780078021558_15_22P","link":"https://yadi.sk/i/DKmxm4SuHn3vOA"},{"isbn_c_p":"9780078021558_15_23P","link":"https://yadi.sk/i/vPJKpvGvpfZ_Vg"},{"isbn_c_p":"9780078021558_15_24P","link":"https://yadi.sk/i/-n9ooGBJ5DlQiQ"},{"isbn_c_p":"9780078021558_15_25P","link":"https://yadi.sk/i/9TkSwoI1fbgghA"},{"isbn_c_p":"9780078021558_15_26P","link":"https://yadi.sk/i/T6OCQXijkLNfwg"},{"isbn_c_p":"9780078021558_15_27P","link":"https://yadi.sk/i/bmR5gHqrv92rsw"},{"isbn_c_p":"9780078021558_15_28P","link":"https://yadi.sk/i/TwMi7sZVTg7K9w"},{"isbn_c_p":"9780078021558_15_29P","link":"https://yadi.sk/i/d6rv1xy0z79IOA"},{"isbn_c_p":"9780078021558_15_2P","link":"https://yadi.sk/i/P_zRFT7ihXChew"},{"isbn_c_p":"9780078021558_15_30P","link":"https://yadi.sk/i/J-haZtJL4i8qyQ"},{"isbn_c_p":"9780078021558_15_31P","link":"https://yadi.sk/i/FoFvMa5NVyjh7Q"},{"isbn_c_p":"9780078021558_15_32P","link":"https://yadi.sk/i/2lNOMDdju7_hyw"},{"isbn_c_p":"9780078021558_15_33P","link":"https://yadi.sk/i/dYJo0Zv9y6BW7Q"},{"isbn_c_p":"9780078021558_15_34P","link":"https://yadi.sk/i/nAaw-lw5f2Hm_Q"},{"isbn_c_p":"9780078021558_15_35P","link":"https://yadi.sk/i/R_TcUys0h0ZCfg"},{"isbn_c_p":"9780078021558_15_36P","link":"https://yadi.sk/i/3soPaPbwNO6syA"},{"isbn_c_p":"9780078021558_15_37P","link":"https://yadi.sk/i/ObKc3XBemQ9ypA"},{"isbn_c_p":"9780078021558_15_38P","link":"https://yadi.sk/i/b-lsRBCMAc05Fw"},{"isbn_c_p":"9780078021558_15_39P","link":"https://yadi.sk/i/4jkjcJunKAE4nw"},{"isbn_c_p":"9780078021558_15_3P","link":"https://yadi.sk/i/dWg-8WU7LCRafw"},{"isbn_c_p":"9780078021558_15_40P","link":"https://yadi.sk/i/TS4pSjumT0nuGQ"},{"isbn_c_p":"9780078021558_15_41P","link":"https://yadi.sk/i/krgUjFPmz1GDTA"},{"isbn_c_p":"9780078021558_15_42P","link":"https://yadi.sk/i/Z854TSpiXNHv1g"},{"isbn_c_p":"9780078021558_15_43P","link":"https://yadi.sk/i/1LIfPLd4dLqoMQ"},{"isbn_c_p":"9780078021558_15_44P","link":"https://yadi.sk/i/-LaeoCMMBPVWQA"},{"isbn_c_p":"9780078021558_15_45P","link":"https://yadi.sk/i/sUVOElkU1Gp9Hg"},{"isbn_c_p":"9780078021558_15_46P","link":"https://yadi.sk/i/26vJfFX9IxUE4Q"},{"isbn_c_p":"9780078021558_15_47P","link":"https://yadi.sk/i/A23O-sJGPAWA6A"},{"isbn_c_p":"9780078021558_15_48P","link":"https://yadi.sk/i/OFzNigeHemDd7Q"},{"isbn_c_p":"9780078021558_15_49P","link":"https://yadi.sk/i/ZQb6IIONzT0gEQ"},{"isbn_c_p":"9780078021558_15_4P","link":"https://yadi.sk/i/hfhSud58QA5lOA"},{"isbn_c_p":"9780078021558_15_50P","link":"https://yadi.sk/i/aAGcAJsgN08lVw"},{"isbn_c_p":"9780078021558_15_51P","link":"https://yadi.sk/i/XQ4_niFZtYUQKQ"},{"isbn_c_p":"9780078021558_15_52P","link":"https://yadi.sk/i/1I4HXhpL4GJufw"},{"isbn_c_p":"9780078021558_15_53P","link":"https://yadi.sk/i/jxWWPXdeyGR9YQ"},{"isbn_c_p":"9780078021558_15_54P","link":"https://yadi.sk/i/0FXsGYYQ79MQzw"},{"isbn_c_p":"9780078021558_15_55P","link":"https://yadi.sk/i/qIVPgTrw-0dDVQ"},{"isbn_c_p":"9780078021558_15_56P","link":"https://yadi.sk/i/vKE7QYee1IXaig"},{"isbn_c_p":"9780078021558_15_57P","link":"https://yadi.sk/i/4A51yRzyhk7Czw"},{"isbn_c_p":"9780078021558_15_58P","link":"https://yadi.sk/i/E1SqkmbWapz7GA"},{"isbn_c_p":"9780078021558_15_59P","link":"https://yadi.sk/i/8wiL6N4Q4rNJJQ"},{"isbn_c_p":"9780078021558_15_5P","link":"https://yadi.sk/i/uvYsEsZXgyLh-A"},{"isbn_c_p":"9780078021558_15_60P","link":"https://yadi.sk/i/vn9nirFD6x2SDQ"},{"isbn_c_p":"9780078021558_15_61P","link":"https://yadi.sk/i/NrETEGcEPoEY7A"},{"isbn_c_p":"9780078021558_15_62P","link":"https://yadi.sk/i/PhuP1qBRWQ9upA"},{"isbn_c_p":"9780078021558_15_63P","link":"https://yadi.sk/i/bm8yWTmCB3TZ3A"},{"isbn_c_p":"9780078021558_15_64P","link":"https://yadi.sk/i/vcZT2GPpwi6Pqg"},{"isbn_c_p":"9780078021558_15_65P","link":"https://yadi.sk/i/GlSb9jp91qro7A"},{"isbn_c_p":"9780078021558_15_66P","link":"https://yadi.sk/i/RjbYemW0JZAPYA"},{"isbn_c_p":"9780078021558_15_67P","link":"https://yadi.sk/i/dWA5F9i2ke5DYg"},{"isbn_c_p":"9780078021558_15_68P","link":"https://yadi.sk/i/8KFv2726_Ec_bA"},{"isbn_c_p":"9780078021558_15_69P","link":"https://yadi.sk/i/UyJPO25i3xl6gw"},{"isbn_c_p":"9780078021558_15_6P","link":"https://yadi.sk/i/GcBSAwZ_DZXyKw"},{"isbn_c_p":"9780078021558_15_70P","link":"https://yadi.sk/i/fIdwMKPe3Ihb7w"},{"isbn_c_p":"9780078021558_15_71P","link":"https://yadi.sk/i/MnfmZRkydUfzvw"},{"isbn_c_p":"9780078021558_15_72P","link":"https://yadi.sk/i/QloN-C_sf7ncxA"},{"isbn_c_p":"9780078021558_15_73P","link":"https://yadi.sk/i/62Lh7hq1J4jlWg"},{"isbn_c_p":"9780078021558_15_74P","link":"https://yadi.sk/i/-3btSveb1X4v_A"},{"isbn_c_p":"9780078021558_15_75P","link":"https://yadi.sk/i/2IWdRUgt6dTOLQ"},{"isbn_c_p":"9780078021558_15_76CP","link":"https://yadi.sk/i/BC3jIm6xoLerNw"},{"isbn_c_p":"9780078021558_15_77CP","link":"https://yadi.sk/i/kHGZyAbmYnu0yw"},{"isbn_c_p":"9780078021558_15_78CP","link":"https://yadi.sk/i/b0ANeJH1guyJoA"},{"isbn_c_p":"9780078021558_15_79CP","link":"https://yadi.sk/i/GCTZo_G50qhtnQ"},{"isbn_c_p":"9780078021558_15_7P","link":"https://yadi.sk/i/PHKFXMc8eZxutA"},{"isbn_c_p":"9780078021558_15_8P","link":"https://yadi.sk/i/1Yjz4aZTuVGbYw"},{"isbn_c_p":"9780078021558_15_9P","link":"https://yadi.sk/i/t5COu6VwQhv38w"}]