[{"isbn_c_p":"9781284070408_9.1_10E","link":"https://yadi.sk/i/qj3Yzl8hZwyDJQ"},{"isbn_c_p":"9781284070408_9.1_11E","link":"https://yadi.sk/i/Gf8-xbRnd5788g"},{"isbn_c_p":"9781284070408_9.1_12E","link":"https://yadi.sk/i/2_iLC_k7777xOQ"},{"isbn_c_p":"9781284070408_9.1_1E","link":"https://yadi.sk/i/LeUmCpBlWBAMrg"},{"isbn_c_p":"9781284070408_9.1_2E","link":"https://yadi.sk/i/hCEkVgDn1r2Ddw"},{"isbn_c_p":"9781284070408_9.1_3E","link":"https://yadi.sk/i/nbsqhRLB5FWDlA"},{"isbn_c_p":"9781284070408_9.1_4E","link":"https://yadi.sk/i/U_sufK10gApa-A"},{"isbn_c_p":"9781284070408_9.1_5E","link":"https://yadi.sk/i/wupsNSLEeWfPNA"},{"isbn_c_p":"9781284070408_9.1_6E","link":"https://yadi.sk/i/tresrdKbjlJ3sQ"},{"isbn_c_p":"9781284070408_9.1_7E","link":"https://yadi.sk/i/tMeUsiLA1ZSWeQ"},{"isbn_c_p":"9781284070408_9.1_8E","link":"https://yadi.sk/i/uPCaWHi4intuYQ"},{"isbn_c_p":"9781284070408_9.1_9E","link":"https://yadi.sk/i/qFbAZ1QGA_aAAg"}]